pyanchorknit/__init__.py
pyanchorknit/cli/main.py
pyanchorknit/utils.py
pyanchorknit/weaving.py
pyanchorknit-0.3.0.dist-info/entry_points.txt
pyanchorknit-0.3.0.dist-info/LICENSE
pyanchorknit-0.3.0.dist-info/WHEEL
pyanchorknit-0.3.0.dist-info/METADATA
pyanchorknit-0.3.0.dist-info/RECORD
