Metadata-Version: 2.1
Name: pyanchorknit
Version: 0.3.0
Summary: Weaving algorithm.
Home-page: https://github.com/CrossNox/pyanchorknit
License: MIT
Author: CrossNox
Author-email: ijmermet@gmail.com
Requires-Python: >=3.7,<4.0
Classifier: License :: OSI Approved :: MIT License
Classifier: Programming Language :: Python :: 3
Classifier: Programming Language :: Python :: 3.7
Classifier: Programming Language :: Python :: 3.8
Classifier: Programming Language :: Python :: 3.9
Classifier: Topic :: Artistic Software
Requires-Dist: opencv-python (>=4.5.3,<5.0.0)
Requires-Dist: pycairo (>=1.20.1,<2.0.0)
Requires-Dist: scikit-image (>=0.18.3,<0.19.0)
Requires-Dist: tqdm (>=4.62.3,<5.0.0)
Requires-Dist: typer (>=0.4.0,<0.5.0)
Project-URL: Repository, https://github.com/CrossNox/pyanchorknit
